pymlip/__init__.py
pymlip/lrlambda.py
tgm_pymlip-0.0.2.data/scripts/pymlip-tune-cosgam
tgm_pymlip-0.0.2.dist-info/LICENSE
tgm_pymlip-0.0.2.dist-info/METADATA
tgm_pymlip-0.0.2.dist-info/WHEEL
tgm_pymlip-0.0.2.dist-info/top_level.txt
tgm_pymlip-0.0.2.dist-info/RECORD
