Metadata-Version: 2.1
Name: tgm-pymlip
Version: 0.0.2
Summary: Package of scripts for MLIP training, validation, and deployment developed while in Szilvasi Group
Author-email: Tristan Maxson <tgmaxson@gmail.com>
License: Attribution 4.0 International
Project-URL: Gitlab, https://gitlab.com/tgmaxson/pymlip
Keywords: mlip,mlff,ai,ml,dft,atomic
Classifier: Intended Audience :: Science/Research
Classifier: Programming Language :: Python :: 3
Classifier: Topic :: Scientific/Engineering
Requires-Python: >=3.7
License-File: LICENSE
Requires-Dist: numpy
Requires-Dist: scipy
Requires-Dist: icecream
